SegEval/__init__.py
SegEval/core.py
segmentationeval-0.1.0.dist-info/METADATA
segmentationeval-0.1.0.dist-info/WHEEL
segmentationeval-0.1.0.dist-info/top_level.txt
segmentationeval-0.1.0.dist-info/RECORD
