Metadata-Version: 2.4
Name: SegmentationEval
Version: 0.1.0
Requires-Dist: numpy
Dynamic: requires-dist
